SparkleWeb/__init__.py
SparkleWeb/SparkleWeb.py
sparkleweb-1.0.3.dist-info/LICENSE
sparkleweb-1.0.3.dist-info/METADATA
sparkleweb-1.0.3.dist-info/WHEEL
sparkleweb-1.0.3.dist-info/RECORD
