Metadata-Version: 2.1
Name: sparkleweb
Version: 1.0.3
Summary: A simple Flask-based SparkleWeb server module.
License: MIT
Author: Tejus Gupta
Author-email: tejus3131@gmail.com
Requires-Python: >=3.11,<4.0
Classifier: License :: OSI Approved :: MIT License
Classifier: Programming Language :: Python :: 3
Classifier: Programming Language :: Python :: 3.11
